feanor/__init__.py
feanor/__main__.py
feanor/builderTool.py
feanor/virtualEnv.py
feanor-1.2.5.dist-info/METADATA
feanor-1.2.5.dist-info/WHEEL
feanor-1.2.5.dist-info/entry_points.txt
feanor-1.2.5.dist-info/top_level.txt
feanor-1.2.5.dist-info/RECORD
