Metadata-Version: 2.1
Name: feanor
Version: 1.2.5
Summary: Python script for simplify automatic build, tests, publish and deploy of projects.
Author-email: Antoine Buirey <antoine.buirey@gmail.com>
Project-URL: homepage, https://github.com/T0ine34/feanor
Project-URL: issues, https://github.com/T0ine34/feanor/issues
Project-URL: source, https://github.com/T0ine34/feanor
Classifier: Programming Language :: Python :: 3
Classifier: License :: OSI Approved :: MIT License
Classifier: Operating System :: OS Independent
Requires-Python: >=3.10
Requires-Dist: gamuLogger
Requires-Dist: feanorTempDir
